debug_tracer/DebugTracer.py
debug_tracer/__init__.py
debug_tracer-0.1.0.dist-info/licenses/LICENSE
debug_tracer-0.1.0.dist-info/METADATA
debug_tracer-0.1.0.dist-info/WHEEL
debug_tracer-0.1.0.dist-info/top_level.txt
debug_tracer-0.1.0.dist-info/RECORD
