Metadata-Version: 2.4
Name: debug-tracer
Version: 0.1.0
Summary: A helpful debug tracer exception i spun together with GPT, not too bad not too good.
Author-email: Glitchy <iamsk8k9@gmail.com>
License: Copyright (C) 2025 "I am called glitchy"
Classifier: Programming Language :: Python :: 3
Classifier: License :: OSI Approved :: GNU Affero General Public License v3
Classifier: Operating System :: OS Independent
Requires-Python: >=3.6
License-File: LICENSE
Dynamic: license-file
